{"rounds_played": 1, "wc_blend_weight": 0.35, "GK": {"top_picks": [{"id": "1099", "name": "Unai Simón", "country": "ESP", "position": "GK", "price": 5.0, "ownership": 7.4, "xpts": 39.6, "model_xpts": 27.1, "remaining_xpts": 25.6, "wc_pts": 14, "last_round": 7, "wc_form": 4.7, "value": 7.928, "one_to_watch": false}, {"id": "183", "name": "Alisson Becker", "country": "BRA", "position": "GK", "price": 5.0, "ownership": 6.5, "xpts": 34.2, "model_xpts": 28.4, "remaining_xpts": 24.2, "wc_pts": 10, "last_round": 8, "wc_form": 3.3, "value": 6.847, "one_to_watch": false}, {"id": "1522", "name": "Thibaut Courtois", "country": "BEL", "position": "GK", "price": 4.9, "ownership": 12.3, "xpts": 33.5, "model_xpts": 27.3, "remaining_xpts": 23.5, "wc_pts": 10, "last_round": 8, "wc_form": 3.3, "value": 6.835, "one_to_watch": false}, {"id": "2010", "name": "Yassine Bounou", "country": "MAR", "position": "GK", "price": 4.7, "ownership": 4.7, "xpts": 31.3, "model_xpts": 19.1, "remaining_xpts": 19.3, "wc_pts": 12, "last_round": 9, "wc_form": 4.0, "value": 6.663, "one_to_watch": false}, {"id": "45", "name": "Emiliano Martínez", "country": "ARG", "position": "GK", "price": 5.0, "ownership": 24.0, "xpts": 30.9, "model_xpts": 30.5, "remaining_xpts": 23.9, "wc_pts": 7, "last_round": 7, "wc_form": 2.3, "value": 6.171, "one_to_watch": false}, {"id": "809", "name": "Bart Verbruggen", "country": "NED", "position": "GK", "price": 4.7, "ownership": 3.1, "xpts": 24.9, "model_xpts": 26.2, "remaining_xpts": 19.9, "wc_pts": 5, "last_round": 4, "wc_form": 1.7, "value": 5.293, "one_to_watch": false}], "rising": [{"id": "1099", "name": "Unai Simón", "country": "ESP", "position": "GK", "price": 5.0, "ownership": 7.4, "xpts": 39.6, "model_xpts": 27.1, "remaining_xpts": 25.6, "wc_pts": 14, "last_round": 7, "wc_form": 4.7, "value": 7.928, "one_to_watch": false, "form_delta": 12.6}, {"id": "2010", "name": "Yassine Bounou", "country": "MAR", "position": "GK", "price": 4.7, "ownership": 4.7, "xpts": 31.3, "model_xpts": 19.1, "remaining_xpts": 19.3, "wc_pts": 12, "last_round": 9, "wc_form": 4.0, "value": 6.663, "one_to_watch": false, "form_delta": 12.2}, {"id": "1522", "name": "Thibaut Courtois", "country": "BEL", "position": "GK", "price": 4.9, "ownership": 12.3, "xpts": 33.5, "model_xpts": 27.3, "remaining_xpts": 23.5, "wc_pts": 10, "last_round": 8, "wc_form": 3.3, "value": 6.835, "one_to_watch": false, "form_delta": 6.2}, {"id": "183", "name": "Alisson Becker", "country": "BRA", "position": "GK", "price": 5.0, "ownership": 6.5, "xpts": 34.2, "model_xpts": 28.4, "remaining_xpts": 24.2, "wc_pts": 10, "last_round": 8, "wc_form": 3.3, "value": 6.847, "one_to_watch": false, "form_delta": 5.8}, {"id": "45", "name": "Emiliano Martínez", "country": "ARG", "position": "GK", "price": 5.0, "ownership": 24.0, "xpts": 30.9, "model_xpts": 30.5, "remaining_xpts": 23.9, "wc_pts": 7, "last_round": 7, "wc_form": 2.3, "value": 6.171, "one_to_watch": false, "form_delta": 0.3}], "falling": [{"id": "338", "name": "Dominik Livakovic", "country": "CRO", "position": "GK", "price": 4.5, "ownership": 1.9, "xpts": 19.1, "model_xpts": 26.9, "remaining_xpts": 18.1, "wc_pts": 1, "last_round": 1, "wc_form": 0.3, "value": 4.242, "one_to_watch": false, "form_delta": -7.9}, {"id": "477", "name": "Jordan Pickford", "country": "ENG", "position": "GK", "price": 4.8, "ownership": 14.6, "xpts": 23.4, "model_xpts": 31.1, "remaining_xpts": 21.4, "wc_pts": 2, "last_round": 2, "wc_form": 0.7, "value": 4.869, "one_to_watch": false, "form_delta": -7.7}, {"id": "506", "name": "Mike Maignan", "country": "FRA", "position": "GK", "price": 5.0, "ownership": 9.2, "xpts": 22.9, "model_xpts": 30.4, "remaining_xpts": 20.9, "wc_pts": 2, "last_round": 2, "wc_form": 0.7, "value": 4.578, "one_to_watch": false, "form_delta": -7.5}, {"id": "1051", "name": "Édouard Mendy", "country": "SEN", "position": "GK", "price": 4.5, "ownership": 1.2, "xpts": 16.1, "model_xpts": 22.3, "remaining_xpts": 15.1, "wc_pts": 1, "last_round": 1, "wc_form": 0.3, "value": 3.567, "one_to_watch": false, "form_delta": -6.2}, {"id": "1569", "name": "Diogo Costa", "country": "POR", "position": "GK", "price": 4.9, "ownership": 9.1, "xpts": 20.3, "model_xpts": 26.4, "remaining_xpts": 18.3, "wc_pts": 2, "last_round": 2, "wc_form": 0.7, "value": 4.141, "one_to_watch": false, "form_delta": -6.1}], "sell_targets": [{"id": "508", "name": "Brice Samba", "country": "FRA", "position": "GK", "price": 4.5, "ownership": 0.2, "xpts": 19.2, "model_xpts": 29.6, "remaining_xpts": 19.2, "wc_pts": 0, "last_round": 0, "wc_form": 0.0, "value": 4.268, "one_to_watch": false}, {"id": "46", "name": "Gerónimo Rulli", "country": "ARG", "position": "GK", "price": 4.5, "ownership": 0.2, "xpts": 18.4, "model_xpts": 28.3, "remaining_xpts": 18.4, "wc_pts": 0, "last_round": 0, "wc_form": 0.0, "value": 4.095, "one_to_watch": false}, {"id": "1316", "name": "Walter Benítez", "country": "ARG", "position": "GK", "price": 4.5, "ownership": 0.0, "xpts": 18.4, "model_xpts": 28.3, "remaining_xpts": 18.4, "wc_pts": 0, "last_round": 0, "wc_form": 0.0, "value": 4.092, "one_to_watch": false}, {"id": "182", "name": "Ederson", "country": "BRA", "position": "GK", "price": 5.0, "ownership": 2.8, "xpts": 18.3, "model_xpts": 28.1, "remaining_xpts": 18.3, "wc_pts": 0, "last_round": 0, "wc_form": 0.0, "value": 3.653, "one_to_watch": false}, {"id": "1343", "name": "Weverton", "country": "BRA", "position": "GK", "price": 4.5, "ownership": 0.1, "xpts": 18.1, "model_xpts": 27.9, "remaining_xpts": 18.1, "wc_pts": 0, "last_round": 0, "wc_form": 0.0, "value": 4.024, "one_to_watch": false}]}, "DEF": {"top_picks": [{"id": "1086", "name": "Aymeric Laporte", "country": "ESP", "position": "DEF", "price": 5.5, "ownership": 5.6, "xpts": 51.0, "model_xpts": 27.6, "remaining_xpts": 30.0, "wc_pts": 21, "last_round": 12, "wc_form": 7.0, "value": 9.28, "one_to_watch": false}, {"id": "1264", "name": "Alexander Freeman", "country": "USA", "position": "DEF", "price": 4.0, "ownership": 1.5, "xpts": 50.4, "model_xpts": 21.7, "remaining_xpts": 27.4, "wc_pts": 23, "last_round": 16, "wc_form": 7.7, "value": 12.59, "one_to_watch": false}, {"id": "2031", "name": "Sergiño Dest", "country": "USA", "position": "DEF", "price": 4.3, "ownership": 4.0, "xpts": 47.4, "model_xpts": 22.0, "remaining_xpts": 26.4, "wc_pts": 21, "last_round": 12, "wc_form": 7.0, "value": 11.015, "one_to_watch": false}, {"id": "1088", "name": "Marc Cucurella", "country": "ESP", "position": "DEF", "price": 5.1, "ownership": 25.6, "xpts": 44.5, "model_xpts": 27.3, "remaining_xpts": 27.5, "wc_pts": 17, "last_round": 10, "wc_form": 5.7, "value": 8.73, "one_to_watch": false}, {"id": "597", "name": "Ramin Rezaeian", "country": "IRN", "position": "DEF", "price": 4.0, "ownership": 0.9, "xpts": 43.5, "model_xpts": 13.6, "remaining_xpts": 21.5, "wc_pts": 22, "last_round": 9, "wc_form": 7.3, "value": 10.879, "one_to_watch": false}, {"id": "740", "name": "Johan Vásquez", "country": "MEX", "position": "DEF", "price": 4.7, "ownership": 3.9, "xpts": 43.4, "model_xpts": 23.1, "remaining_xpts": 25.4, "wc_pts": 18, "last_round": 9, "wc_form": 6.0, "value": 9.232, "one_to_watch": false}, {"id": "742", "name": "Jesús Gallardo", "country": "MEX", "position": "DEF", "price": 4.7, "ownership": 0.9, "xpts": 43.4, "model_xpts": 23.1, "remaining_xpts": 25.4, "wc_pts": 18, "last_round": 9, "wc_form": 6.0, "value": 9.232, "one_to_watch": false}, {"id": "525", "name": "Nathaniel Brown", "country": "GER", "position": "DEF", "price": 4.7, "ownership": 6.3, "xpts": 43.2, "model_xpts": 27.7, "remaining_xpts": 27.2, "wc_pts": 16, "last_round": 2, "wc_form": 5.3, "value": 9.186, "one_to_watch": false}, {"id": "1089", "name": "Pau Cubarsí", "country": "ESP", "position": "DEF", "price": 5.0, "ownership": 5.8, "xpts": 39.7, "model_xpts": 27.2, "remaining_xpts": 25.7, "wc_pts": 14, "last_round": 7, "wc_form": 4.7, "value": 7.949, "one_to_watch": false}, {"id": "526", "name": "Nico Schlotterbeck", "country": "GER", "position": "DEF", "price": 5.3, "ownership": 6.1, "xpts": 37.2, "model_xpts": 28.2, "remaining_xpts": 25.2, "wc_pts": 12, "last_round": 1, "wc_form": 4.0, "value": 7.026, "one_to_watch": false}], "rising": [{"id": "597", "name": "Ramin Rezaeian", "country": "IRN", "position": "DEF", "price": 4.0, "ownership": 0.9, "xpts": 43.5, "model_xpts": 13.6, "remaining_xpts": 21.5, "wc_pts": 22, "last_round": 9, "wc_form": 7.3, "value": 10.879, "one_to_watch": false, "form_delta": 29.9}, {"id": "1264", "name": "Alexander Freeman", "country": "USA", "position": "DEF", "price": 4.0, "ownership": 1.5, "xpts": 50.4, "model_xpts": 21.7, "remaining_xpts": 27.4, "wc_pts": 23, "last_round": 16, "wc_form": 7.7, "value": 12.59, "one_to_watch": false, "form_delta": 28.6}, {"id": "2031", "name": "Sergiño Dest", "country": "USA", "position": "DEF", "price": 4.3, "ownership": 4.0, "xpts": 47.4, "model_xpts": 22.0, "remaining_xpts": 26.4, "wc_pts": 21, "last_round": 12, "wc_form": 7.0, "value": 11.015, "one_to_watch": false, "form_delta": 25.4}, {"id": "1086", "name": "Aymeric Laporte", "country": "ESP", "position": "DEF", "price": 5.5, "ownership": 5.6, "xpts": 51.0, "model_xpts": 27.6, "remaining_xpts": 30.0, "wc_pts": 21, "last_round": 12, "wc_form": 7.0, "value": 9.28, "one_to_watch": false, "form_delta": 23.4}, {"id": "740", "name": "Johan Vásquez", "country": "MEX", "position": "DEF", "price": 4.7, "ownership": 3.9, "xpts": 43.4, "model_xpts": 23.1, "remaining_xpts": 25.4, "wc_pts": 18, "last_round": 9, "wc_form": 6.0, "value": 9.232, "one_to_watch": false, "form_delta": 20.3}], "falling": [{"id": "1709", "name": "Reece James", "country": "ENG", "position": "DEF", "price": 5.2, "ownership": 4.4, "xpts": 21.7, "model_xpts": 31.0, "remaining_xpts": 20.7, "wc_pts": 1, "last_round": 1, "wc_form": 0.3, "value": 4.176, "one_to_watch": false, "form_delta": -9.3}, {"id": "461", "name": "Marc Guéhi", "country": "ENG", "position": "DEF", "price": 5.1, "ownership": 6.2, "xpts": 21.7, "model_xpts": 30.9, "remaining_xpts": 20.7, "wc_pts": 1, "last_round": 1, "wc_form": 0.3, "value": 4.245, "one_to_watch": false, "form_delta": -9.2}, {"id": "463", "name": "Ezri Konsa", "country": "ENG", "position": "DEF", "price": 4.8, "ownership": 1.0, "xpts": 21.5, "model_xpts": 30.6, "remaining_xpts": 20.5, "wc_pts": 1, "last_round": 1, "wc_form": 0.3, "value": 4.47, "one_to_watch": false, "form_delta": -9.1}, {"id": "457", "name": "Nico O'Reilly", "country": "ENG", "position": "DEF", "price": 4.7, "ownership": 11.8, "xpts": 21.4, "model_xpts": 30.5, "remaining_xpts": 20.4, "wc_pts": 1, "last_round": 1, "wc_form": 0.3, "value": 4.551, "one_to_watch": false, "form_delta": -9.1}, {"id": "466", "name": "John Stones", "country": "ENG", "position": "DEF", "price": 4.6, "ownership": 1.5, "xpts": 21.3, "model_xpts": 30.4, "remaining_xpts": 20.3, "wc_pts": 1, "last_round": 1, "wc_form": 0.3, "value": 4.636, "one_to_watch": false, "form_delta": -9.1}], "sell_targets": [{"id": "496", "name": "Lucas Hernández", "country": "FRA", "position": "DEF", "price": 5.2, "ownership": 1.9, "xpts": 19.9, "model_xpts": 30.7, "remaining_xpts": 19.9, "wc_pts": 0, "last_round": 0, "wc_form": 0.0, "value": 3.832, "one_to_watch": false}, {"id": "499", "name": "Malo Gusto", "country": "FRA", "position": "DEF", "price": 5.1, "ownership": 0.5, "xpts": 19.9, "model_xpts": 30.6, "remaining_xpts": 19.9, "wc_pts": 0, "last_round": 0, "wc_form": 0.0, "value": 3.896, "one_to_watch": false}, {"id": "498", "name": "Lucas Digne", "country": "FRA", "position": "DEF", "price": 5.0, "ownership": 0.9, "xpts": 19.8, "model_xpts": 30.5, "remaining_xpts": 19.8, "wc_pts": 0, "last_round": 0, "wc_form": 0.0, "value": 3.961, "one_to_watch": false}, {"id": "459", "name": "Tino Livramento", "country": "ENG", "position": "DEF", "price": 4.6, "ownership": 0.2, "xpts": 19.7, "model_xpts": 30.4, "remaining_xpts": 19.7, "wc_pts": 0, "last_round": 0, "wc_form": 0.0, "value": 4.293, "one_to_watch": false}, {"id": "495", "name": "Ibrahima Konaté", "country": "FRA", "position": "DEF", "price": 4.9, "ownership": 1.9, "xpts": 19.7, "model_xpts": 30.4, "remaining_xpts": 19.7, "wc_pts": 0, "last_round": 0, "wc_form": 0.0, "value": 4.03, "one_to_watch": false}]}, "MID": {"top_picks": [{"id": "173", "name": "Vinícius Júnior", "country": "BRA", "position": "MID", "price": 10.0, "ownership": 18.9, "xpts": 48.6, "model_xpts": 26.2, "remaining_xpts": 28.6, "wc_pts": 20, "last_round": 12, "wc_form": 6.7, "value": 4.856, "one_to_watch": false}, {"id": "1223", "name": "Maxi Araújo", "country": "URU", "position": "MID", "price": 6.4, "ownership": 0.6, "xpts": 44.1, "model_xpts": 12.1, "remaining_xpts": 21.1, "wc_pts": 23, "last_round": 13, "wc_form": 7.7, "value": 6.893, "one_to_watch": false}, {"id": "1601", "name": "Felix Nmecha", "country": "GER", "position": "MID", "price": 5.6, "ownership": 3.7, "xpts": 43.6, "model_xpts": 11.4, "remaining_xpts": 20.6, "wc_pts": 23, "last_round": 10, "wc_form": 7.7, "value": 7.79, "one_to_watch": false}, {"id": "682", "name": "Daichi Kamada", "country": "JPN", "position": "MID", "price": 5.8, "ownership": 2.3, "xpts": 41.5, "model_xpts": 10.6, "remaining_xpts": 19.5, "wc_pts": 22, "last_round": 11, "wc_form": 7.3, "value": 7.159, "one_to_watch": false}, {"id": "2044", "name": "Crysencio Summerville", "country": "NED", "position": "MID", "price": 5.3, "ownership": 2.9, "xpts": 40.1, "model_xpts": 10.8, "remaining_xpts": 19.1, "wc_pts": 21, "last_round": 12, "wc_form": 7.0, "value": 7.564, "one_to_watch": false}, {"id": "792", "name": "Ismael Saibari", "country": "MAR", "position": "MID", "price": 6.8, "ownership": 4.4, "xpts": 40.0, "model_xpts": 10.7, "remaining_xpts": 19.0, "wc_pts": 21, "last_round": 11, "wc_form": 7.0, "value": 5.886, "one_to_watch": false}, {"id": "1597", "name": "Mohamed Salah", "country": "EGY", "position": "MID", "price": 10.0, "ownership": 4.8, "xpts": 38.6, "model_xpts": 15.7, "remaining_xpts": 20.6, "wc_pts": 18, "last_round": 11, "wc_form": 6.0, "value": 3.858, "one_to_watch": false}, {"id": "1158", "name": "Rubén Vargas", "country": "SUI", "position": "MID", "price": 6.8, "ownership": 0.6, "xpts": 36.6, "model_xpts": 12.7, "remaining_xpts": 18.6, "wc_pts": 18, "last_round": 15, "wc_form": 6.0, "value": 5.378, "one_to_watch": false}, {"id": "671", "name": "Keito Nakamura", "country": "JPN", "position": "MID", "price": 5.5, "ownership": 1.8, "xpts": 34.9, "model_xpts": 10.1, "remaining_xpts": 16.9, "wc_pts": 18, "last_round": 8, "wc_form": 6.0, "value": 6.343, "one_to_watch": false}, {"id": "1114", "name": "Yasin Ayari", "country": "SWE", "position": "MID", "price": 5.3, "ownership": 2.6, "xpts": 33.9, "model_xpts": 8.5, "remaining_xpts": 15.9, "wc_pts": 18, "last_round": 1, "wc_form": 6.0, "value": 6.387, "one_to_watch": false}], "rising": [{"id": "1601", "name": "Felix Nmecha", "country": "GER", "position": "MID", "price": 5.6, "ownership": 3.7, "xpts": 43.6, "model_xpts": 11.4, "remaining_xpts": 20.6, "wc_pts": 23, "last_round": 10, "wc_form": 7.7, "value": 7.79, "one_to_watch": false, "form_delta": 32.2}, {"id": "1223", "name": "Maxi Araújo", "country": "URU", "position": "MID", "price": 6.4, "ownership": 0.6, "xpts": 44.1, "model_xpts": 12.1, "remaining_xpts": 21.1, "wc_pts": 23, "last_round": 13, "wc_form": 7.7, "value": 6.893, "one_to_watch": false, "form_delta": 32.0}, {"id": "682", "name": "Daichi Kamada", "country": "JPN", "position": "MID", "price": 5.8, "ownership": 2.3, "xpts": 41.5, "model_xpts": 10.6, "remaining_xpts": 19.5, "wc_pts": 22, "last_round": 11, "wc_form": 7.3, "value": 7.159, "one_to_watch": false, "form_delta": 30.9}, {"id": "792", "name": "Ismael Saibari", "country": "MAR", "position": "MID", "price": 6.8, "ownership": 4.4, "xpts": 40.0, "model_xpts": 10.7, "remaining_xpts": 19.0, "wc_pts": 21, "last_round": 11, "wc_form": 7.0, "value": 5.886, "one_to_watch": false, "form_delta": 29.3}, {"id": "2044", "name": "Crysencio Summerville", "country": "NED", "position": "MID", "price": 5.3, "ownership": 2.9, "xpts": 40.1, "model_xpts": 10.8, "remaining_xpts": 19.1, "wc_pts": 21, "last_round": 12, "wc_form": 7.0, "value": 7.564, "one_to_watch": false, "form_delta": 29.3}], "falling": [{"id": "939", "name": "Bruno Fernandes", "country": "POR", "position": "MID", "price": 8.5, "ownership": 45.0, "xpts": 22.1, "model_xpts": 26.7, "remaining_xpts": 19.1, "wc_pts": 3, "last_round": 3, "wc_form": 1.0, "value": 2.597, "one_to_watch": false, "form_delta": -4.6}, {"id": "176", "name": "Gabriel Martinelli", "country": "BRA", "position": "MID", "price": 6.5, "ownership": 0.6, "xpts": 12.8, "model_xpts": 17.2, "remaining_xpts": 11.8, "wc_pts": 1, "last_round": 1, "wc_form": 0.3, "value": 1.966, "one_to_watch": false, "form_delta": -4.5}, {"id": "516", "name": "Rayan Cherki", "country": "FRA", "position": "MID", "price": 8.0, "ownership": 5.7, "xpts": 12.2, "model_xpts": 16.4, "remaining_xpts": 11.2, "wc_pts": 1, "last_round": 1, "wc_form": 0.3, "value": 1.528, "one_to_watch": false, "form_delta": -4.2}, {"id": "1696", "name": "Sadio Mané", "country": "SEN", "position": "MID", "price": 7.6, "ownership": 2.0, "xpts": 16.5, "model_xpts": 20.6, "remaining_xpts": 14.5, "wc_pts": 2, "last_round": 2, "wc_form": 0.7, "value": 2.176, "one_to_watch": false, "form_delta": -4.1}, {"id": "501", "name": "Ousmane Dembélé", "country": "FRA", "position": "MID", "price": 10.0, "ownership": 15.3, "xpts": 20.9, "model_xpts": 24.9, "remaining_xpts": 17.9, "wc_pts": 3, "last_round": 3, "wc_form": 1.0, "value": 2.09, "one_to_watch": false, "form_delta": -4.0}], "sell_targets": [{"id": "1369", "name": "Neymar", "country": "BRA", "position": "MID", "price": 7.2, "ownership": 2.5, "xpts": 14.9, "model_xpts": 23.0, "remaining_xpts": 14.9, "wc_pts": 0, "last_round": 0, "wc_form": 0.0, "value": 2.073, "one_to_watch": false}, {"id": "1710", "name": "Eberechi Eze", "country": "ENG", "position": "MID", "price": 8.0, "ownership": 1.1, "xpts": 10.7, "model_xpts": 16.5, "remaining_xpts": 10.7, "wc_pts": 0, "last_round": 0, "wc_form": 0.0, "value": 1.343, "one_to_watch": false}, {"id": "1572", "name": "Bernardo Silva", "country": "POR", "position": "MID", "price": 7.8, "ownership": 2.0, "xpts": 9.7, "model_xpts": 14.9, "remaining_xpts": 9.7, "wc_pts": 0, "last_round": 0, "wc_form": 0.0, "value": 1.245, "one_to_watch": false}, {"id": "1327", "name": "Emiliano Buendía", "country": "ARG", "position": "MID", "price": 6.5, "ownership": 0.0, "xpts": 8.5, "model_xpts": 13.1, "remaining_xpts": 8.5, "wc_pts": 0, "last_round": 0, "wc_form": 0.0, "value": 1.311, "one_to_watch": false}, {"id": "514", "name": "Maghnes Akliouche", "country": "FRA", "position": "MID", "price": 6.4, "ownership": 0.0, "xpts": 8.4, "model_xpts": 13.0, "remaining_xpts": 8.4, "wc_pts": 0, "last_round": 0, "wc_form": 0.0, "value": 1.32, "one_to_watch": false}]}, "FWD": {"top_picks": [{"id": "38", "name": "Lionel Messi", "country": "ARG", "position": "FWD", "price": 10.0, "ownership": 25.8, "xpts": 53.4, "model_xpts": 36.0, "remaining_xpts": 34.4, "wc_pts": 19, "last_round": 19, "wc_form": 6.3, "value": 5.335, "one_to_watch": false}, {"id": "531", "name": "Deniz Undav", "country": "GER", "position": "FWD", "price": 6.6, "ownership": 1.5, "xpts": 53.1, "model_xpts": 13.9, "remaining_xpts": 25.1, "wc_pts": 28, "last_round": 14, "wc_form": 9.3, "value": 8.052, "one_to_watch": false}, {"id": "226", "name": "Jonathan David", "country": "CAN", "position": "FWD", "price": 7.0, "ownership": 1.4, "xpts": 48.5, "model_xpts": 11.7, "remaining_xpts": 22.5, "wc_pts": 26, "last_round": 24, "wc_form": 8.7, "value": 6.932, "one_to_watch": false}, {"id": "500", "name": "Kylian Mbappé", "country": "FRA", "position": "FWD", "price": 10.5, "ownership": 55.2, "xpts": 46.7, "model_xpts": 37.9, "remaining_xpts": 32.7, "wc_pts": 14, "last_round": 14, "wc_form": 4.7, "value": 4.444, "one_to_watch": false}, {"id": "468", "name": "Harry Kane", "country": "ENG", "position": "FWD", "price": 10.5, "ownership": 38.6, "xpts": 46.0, "model_xpts": 39.2, "remaining_xpts": 33.0, "wc_pts": 13, "last_round": 13, "wc_form": 4.3, "value": 4.379, "one_to_watch": false}, {"id": "1520", "name": "Alexander Isak", "country": "SWE", "position": "FWD", "price": 8.0, "ownership": 4.0, "xpts": 44.7, "model_xpts": 13.0, "remaining_xpts": 21.7, "wc_pts": 23, "last_round": 7, "wc_form": 7.7, "value": 5.586, "one_to_watch": false}, {"id": "855", "name": "Erling Haaland", "country": "NOR", "position": "FWD", "price": 10.5, "ownership": 30.6, "xpts": 44.0, "model_xpts": 26.6, "remaining_xpts": 27.0, "wc_pts": 17, "last_round": 17, "wc_form": 5.7, "value": 4.194, "one_to_watch": false}, {"id": "804", "name": "Cody Gakpo", "country": "NED", "position": "FWD", "price": 7.7, "ownership": 4.0, "xpts": 43.7, "model_xpts": 16.4, "remaining_xpts": 22.7, "wc_pts": 21, "last_round": 19, "wc_form": 7.0, "value": 5.676, "one_to_watch": false}], "rising": [{"id": "531", "name": "Deniz Undav", "country": "GER", "position": "FWD", "price": 6.6, "ownership": 1.5, "xpts": 53.1, "model_xpts": 13.9, "remaining_xpts": 25.1, "wc_pts": 28, "last_round": 14, "wc_form": 9.3, "value": 8.052, "one_to_watch": false, "form_delta": 39.2}, {"id": "226", "name": "Jonathan David", "country": "CAN", "position": "FWD", "price": 7.0, "ownership": 1.4, "xpts": 48.5, "model_xpts": 11.7, "remaining_xpts": 22.5, "wc_pts": 26, "last_round": 24, "wc_form": 8.7, "value": 6.932, "one_to_watch": false, "form_delta": 36.9}, {"id": "1520", "name": "Alexander Isak", "country": "SWE", "position": "FWD", "price": 8.0, "ownership": 4.0, "xpts": 44.7, "model_xpts": 13.0, "remaining_xpts": 21.7, "wc_pts": 23, "last_round": 7, "wc_form": 7.7, "value": 5.586, "one_to_watch": false, "form_delta": 31.7}, {"id": "227", "name": "Cyle Larin", "country": "CAN", "position": "FWD", "price": 6.2, "ownership": 0.2, "xpts": 39.7, "model_xpts": 10.2, "remaining_xpts": 18.7, "wc_pts": 21, "last_round": 13, "wc_form": 7.0, "value": 6.408, "one_to_watch": false, "form_delta": 29.5}, {"id": "804", "name": "Cody Gakpo", "country": "NED", "position": "FWD", "price": 7.7, "ownership": 4.0, "xpts": 43.7, "model_xpts": 16.4, "remaining_xpts": 22.7, "wc_pts": 21, "last_round": 19, "wc_form": 7.0, "value": 5.676, "one_to_watch": false, "form_delta": 27.3}], "falling": [{"id": "1573", "name": "Cristiano Ronaldo", "country": "POR", "position": "FWD", "price": 10.0, "ownership": 9.6, "xpts": 24.6, "model_xpts": 33.0, "remaining_xpts": 22.6, "wc_pts": 2, "last_round": 2, "wc_form": 0.7, "value": 2.462, "one_to_watch": false, "form_delta": -8.4}, {"id": "124", "name": "Romelu Lukaku", "country": "BEL", "position": "FWD", "price": 7.4, "ownership": 1.8, "xpts": 22.4, "model_xpts": 29.6, "remaining_xpts": 20.4, "wc_pts": 2, "last_round": 1, "wc_form": 0.7, "value": 3.022, "one_to_watch": false, "form_delta": -7.2}, {"id": "1236", "name": "Darwin Núñez", "country": "URU", "position": "FWD", "price": 7.5, "ownership": 1.2, "xpts": 19.1, "model_xpts": 24.5, "remaining_xpts": 17.1, "wc_pts": 2, "last_round": 1, "wc_form": 0.7, "value": 2.546, "one_to_watch": false, "form_delta": -5.4}, {"id": "1338", "name": "Lautaro Martínez", "country": "ARG", "position": "FWD", "price": 8.8, "ownership": 3.0, "xpts": 14.2, "model_xpts": 19.4, "remaining_xpts": 13.2, "wc_pts": 1, "last_round": 1, "wc_form": 0.3, "value": 1.608, "one_to_watch": false, "form_delta": -5.2}, {"id": "39", "name": "Julián Alvarez", "country": "ARG", "position": "FWD", "price": 8.6, "ownership": 11.7, "xpts": 14.1, "model_xpts": 19.3, "remaining_xpts": 13.1, "wc_pts": 1, "last_round": 1, "wc_form": 0.3, "value": 1.64, "one_to_watch": false, "form_delta": -5.2}], "sell_targets": [{"id": "1712", "name": "Ivan Toney", "country": "ENG", "position": "FWD", "price": 7.5, "ownership": 0.2, "xpts": 18.6, "model_xpts": 28.7, "remaining_xpts": 18.6, "wc_pts": 0, "last_round": 0, "wc_form": 0.0, "value": 2.484, "one_to_watch": false}, {"id": "1711", "name": "Ollie Watkins", "country": "ENG", "position": "FWD", "price": 7.9, "ownership": 1.0, "xpts": 11.4, "model_xpts": 17.6, "remaining_xpts": 11.4, "wc_pts": 0, "last_round": 0, "wc_form": 0.0, "value": 1.449, "one_to_watch": false}, {"id": "502", "name": "Marcus Thuram", "country": "FRA", "position": "FWD", "price": 7.5, "ownership": 0.5, "xpts": 10.5, "model_xpts": 16.2, "remaining_xpts": 10.5, "wc_pts": 0, "last_round": 0, "wc_form": 0.0, "value": 1.402, "one_to_watch": false}, {"id": "532", "name": "Nick Woltemade", "country": "GER", "position": "FWD", "price": 7.2, "ownership": 0.7, "xpts": 9.9, "model_xpts": 15.3, "remaining_xpts": 9.9, "wc_pts": 0, "last_round": 0, "wc_form": 0.0, "value": 1.379, "one_to_watch": false}, {"id": "332", "name": "Ante Budimir", "country": "CRO", "position": "FWD", "price": 6.8, "ownership": 0.2, "xpts": 9.5, "model_xpts": 14.6, "remaining_xpts": 9.5, "wc_pts": 0, "last_round": 0, "wc_form": 0.0, "value": 1.396, "one_to_watch": false}]}}